pigen/__init__.py
pigen/cli.py
pigen/pigen.py
pigen-0.1.5.dist-info/AUTHORS.rst
pigen-0.1.5.dist-info/LICENSE
pigen-0.1.5.dist-info/METADATA
pigen-0.1.5.dist-info/WHEEL
pigen-0.1.5.dist-info/top_level.txt
pigen-0.1.5.dist-info/RECORD
