Metadata-Version: 2.1
Name: pigen
Version: 0.1.5
Summary: A collection of Pi generators.
Home-page: https://github.com/stkterry/pigen
Author: Steven K Terry
Author-email: stkterry@gmail.com
License: MIT license
Keywords: pigen
Platform: UNKNOWN
Classifier: Development Status :: 2 - Pre-Alpha
Classifier: Intended Audience :: Developers
Classifier: License :: OSI Approved :: MIT License
Classifier: Natural Language :: English
Classifier: Programming Language :: Python :: 3.5
Classifier: Programming Language :: Python :: 3.6
Classifier: Programming Language :: Python :: 3.7
Classifier: Programming Language :: Python :: 3.8
Requires-Python: >=3.5
Requires-Dist: Click (>=7.0)
Requires-Dist: gmpy2 (>=2.0.8)
Requires-Dist: mock (>=3)
